vgridpandas/__init__.py
vgridpandas/a5pandas/__init__.py
vgridpandas/a5pandas/a5geom.py
vgridpandas/a5pandas/a5pandas.py
vgridpandas/dggalpandas/__init__.py
vgridpandas/dggalpandas/dggalgeom.py
vgridpandas/dggalpandas/dggalpandas.py
vgridpandas/dggridpandas/__init__.py
vgridpandas/dggridpandas/dggridpandas.py
vgridpandas/easepandas/__init__.py
vgridpandas/easepandas/easegeom.py
vgridpandas/easepandas/easepandas.py
vgridpandas/garspandas/__init__.py
vgridpandas/garspandas/garspandas.py
vgridpandas/geohashpandas/__init__.py
vgridpandas/geohashpandas/geohashgeom.py
vgridpandas/geohashpandas/geohashpandas.py
vgridpandas/georefpandas/__init__.py
vgridpandas/georefpandas/georefpandas.py
vgridpandas/h3pandas/__init__.py
vgridpandas/h3pandas/h3geom.py
vgridpandas/h3pandas/h3pandas.py
vgridpandas/isea3hpandas/__init__.py
vgridpandas/isea3hpandas/isea3hgeom.py
vgridpandas/isea3hpandas/isea3hpandas.py
vgridpandas/isea4tpandas/__init__.py
vgridpandas/isea4tpandas/isea4tgeom.py
vgridpandas/isea4tpandas/isea4tpandas.py
vgridpandas/maidenheadpandas/__init__.py
vgridpandas/maidenheadpandas/maidenheadpandas.py
vgridpandas/mgrspandas/__init__.py
vgridpandas/mgrspandas/mgrspandas.py
vgridpandas/olcpandas/__init__.py
vgridpandas/olcpandas/olcgeom.py
vgridpandas/olcpandas/olcpandas.py
vgridpandas/qtmpandas/__init__.py
vgridpandas/qtmpandas/qtmgeom.py
vgridpandas/qtmpandas/qtmpandas.py
vgridpandas/quadkeypandas/__init__.py
vgridpandas/quadkeypandas/quadkeygeom.py
vgridpandas/quadkeypandas/quadkeypandas.py
vgridpandas/rhealpixpandas/__init__.py
vgridpandas/rhealpixpandas/rhealpixgeom.py
vgridpandas/rhealpixpandas/rhealpixpandas.py
vgridpandas/s2pandas/__init__.py
vgridpandas/s2pandas/s2geom.py
vgridpandas/s2pandas/s2pandas.py
vgridpandas/tilecodepandas/__init__.py
vgridpandas/tilecodepandas/tilecodegeom.py
vgridpandas/tilecodepandas/tilecodepandas.py
vgridpandas/utils/__init__.py
vgridpandas/utils/const.py
vgridpandas/utils/decorator.py
vgridpandas/utils/functools.py
vgridpandas-1.0.7.dist-info/licenses/LICENSE
vgridpandas-1.0.7.dist-info/METADATA
vgridpandas-1.0.7.dist-info/WHEEL
vgridpandas-1.0.7.dist-info/top_level.txt
vgridpandas-1.0.7.dist-info/RECORD
