Metadata-Version: 2.4
Name: vgridpandas
Version: 1.0.7
Summary: Integration of Vgrid DGGS into Pandas and GeoPandas
Author-email: Thang Quach <quachdongthang@gmail.com>
License-Expression: MIT
Project-URL: Homepage, https://github.com/opengeoshub/vgridpandas
Project-URL: Download, https://github.com/opengeoshub/vgridpandas/releases
Requires-Python: >=3.9
License-File: LICENSE
Requires-Dist: vgrid>=1.4.0
Provides-Extra: test
Requires-Dist: pytest; extra == "test"
Requires-Dist: pytest-cov; extra == "test"
Requires-Dist: ruff; extra == "test"
Dynamic: license-file
